loginhelper/__init__.py
loginhelper/const.py
loginhelper/main.py
loginhelper-0.0.13.dist-info/AUTHORS
loginhelper-0.0.13.dist-info/LICENSE
loginhelper-0.0.13.dist-info/METADATA
loginhelper-0.0.13.dist-info/WHEEL
loginhelper-0.0.13.dist-info/pbr.json
loginhelper-0.0.13.dist-info/top_level.txt
loginhelper-0.0.13.dist-info/RECORD
