Metadata-Version: 2.1
Name: loginhelper
Version: 0.0.13
Summary: The handle of the login method for auto test
Home-page: UNKNOWN
Author: ssfanli
Author-email: freedomlidi@163.com
License: MIT
Platform: UNKNOWN
Classifier: Programming Language :: Python :: 3
Classifier: License :: OSI Approved :: MIT License
Classifier: Operating System :: OS Independent
Requires-Python: >=3.6
Requires-Dist: uiautomator2
Requires-Dist: facebook-wda
Requires-Dist: tidevice
Requires-Dist: loguru
